README.rst
setup.py
AGEpy/AGEpy.py
AGEpy/__init__.py
AGEpy/bed.py
AGEpy/biom.py
AGEpy/blast.py
AGEpy/cytoscape.py
AGEpy/david.py
AGEpy/fasta.py
AGEpy/go.py
AGEpy/gtf.py
AGEpy/homology.py
AGEpy/kegg.py
AGEpy/meme.py
AGEpy/plots.py
AGEpy/rbiom.py
AGEpy/sam.py
AGEpy.egg-info/PKG-INFO
AGEpy.egg-info/SOURCES.txt
AGEpy.egg-info/dependency_links.txt
AGEpy.egg-info/not-zip-safe
AGEpy.egg-info/requires.txt
AGEpy.egg-info/top_level.txt
bin/aDiff
bin/abed
bin/blasto
bin/david
bin/obo2tsv