Metadata-Version: 1.0
Name: AGEpy
Version: 0.7.0
Summary: Bioinformatics tools for Python developed at the MPI for Biology of Ageing
Home-page: https://github.com/mpg-age-bioinformatics/AGEpy
Author: Bioinformatics Core Facility of the Max Planck Institute for Biology of Ageing
Author-email: bioinformatics@age.mpg.de
License: MIT
Platform: UNKNOWN
